<BackupInst xmlns="http://www.microsoft.com/GroupPolicy/GPOOperations/Manifest"><GPOGuid><![CDATA[{06C47A7C-E1E1-4320-B680-E230F0B13BAA}]]></GPOGuid><GPODomain><![CDATA[HYD.LOCAL]]></GPODomain><GPODomainGuid><![CDATA[{7d6d1905-6f88-426c-ab14-0ad8be140ebf}]]></GPODomainGuid><GPODomainController><![CDATA[HYD-DC01.HYD.LOCAL]]></GPODomainController><BackupTime><![CDATA[2022-11-04T02:45:19]]></BackupTime><ID><![CDATA[{6E208BCF-BA36-4A89-B3C0-6DB6BB3E2841}]]></ID><Comment><![CDATA[]]></Comment><GPODisplayName><![CDATA[Windows Remote Management]]></GPODisplayName></BackupInst>
